threadsnake/__init__.py
threadsnake/html/__init__.py
threadsnake/html/tools.py
threadsnake/http/__init__.py
threadsnake/http/application.py
threadsnake/http/router.py
threadsnake/http/types.py
threadsnake/http/core/__init__.py
threadsnake/http/core/common.py
threadsnake/http/core/constants.py
threadsnake/http/core/httprequest.py
threadsnake/http/core/httpresponse.py
threadsnake/http/core/httpserver.py
threadsnake/http/core/server.py
threadsnake/http/core/session.py
threadsnake/http/core/values/__init__.py
threadsnake/http/core/values/contenttypes.py
threadsnake/http/core/values/responsecodes.py
threadsnake/http/middlewares/__init__.py
threadsnake/http/middlewares/app.py
threadsnake/http/middlewares/authorization.py
threadsnake/http/middlewares/bodyparser.py
threadsnake/http/middlewares/cors.py
threadsnake/http/middlewares/defaultheaders.py
threadsnake/http/middlewares/jsonbodyparser.py
threadsnake/http/middlewares/multipartformdataparser.py
threadsnake/http/middlewares/requests.py
threadsnake/http/middlewares/session.py
threadsnake/http/middlewares/static.py
threadsnake/http/middlewares/timemeassure.py
threadsnake/http/tools/__init__.py
threadsnake/http/tools/common.py
threadsnake/http/tools/routing.py
threadsnake/turbo/__init__.py
threadsnake-1.0.12.dist-info/LICENSE
threadsnake-1.0.12.dist-info/METADATA
threadsnake-1.0.12.dist-info/WHEEL
threadsnake-1.0.12.dist-info/top_level.txt
threadsnake-1.0.12.dist-info/RECORD
