Metadata-Version: 2.1
Name: threadsnake
Version: 1.0.12
Summary: A tiny experimental server-side express-like library
Home-page: https://github.com/LostSavannah/threadsnake
Author: Erick Fernando Mora Ramirez
Author-email: erickfernandomoraramirez@gmail.com
Project-URL: Bug Tracker, https://dev.moradev.dev/threadsnake/issues
Project-URL: Documentation, https://dev.moradev.dev/threadsnake/documentation
Project-URL: Examples, https://dev.moradev.dev/threadsnake/examples
Classifier: Programming Language :: Python :: 3
Classifier: Development Status :: 4 - Beta
Classifier: License :: OSI Approved :: GNU General Public License v3 (GPLv3)
Classifier: Operating System :: OS Independent
Requires-Python: >=3.6
License-File: LICENSE
